{
    "chain_name": "nolus",
    "coingecko": "nolus",
    "api": ["https://api.nolus.indonode.net/"],
    "rpc": ["https://rpc.nolus.indonode.net/"],
    "snapshot_provider": "25818648522d46a18975a1e33966acc8273debeb@rpc.nolus.indonode.net:29656",
    "sdk_version": "0.45.15",
    "coin_type": "118",
    "min_tx_fee": "2500",
    "addr_prefix": "nolus",
    "logo": "/logos/nolus.png",
    "assets": [{
        "base": "unls",
        "symbol": "NOLUS",
        "exponent": "6",
        "coingecko_id": "nolus",
        "logo": "/logos/nolus.png"
    }]
}